pure_array/__init__.py
pure_array/ndarray.py
pure_array/py.typed
pure_array-0.1.0.dist-info/LICENSE
pure_array-0.1.0.dist-info/METADATA
pure_array-0.1.0.dist-info/WHEEL
pure_array-0.1.0.dist-info/top_level.txt
pure_array-0.1.0.dist-info/RECORD
