Metadata-Version: 2.1
Name: pure-array
Version: 0.1.0
Summary: A pure python implementation of numpy array
Home-page: https://github.com/ferranSanchezLlado/pure_array.git
Author: Ferran Sanchez Llado
Author-email: ferransll@gmail.com
License: MIT
Platform: any
Classifier: Programming Language :: Python :: 3
Classifier: Programming Language :: Python :: 3 :: Only
Classifier: License :: OSI Approved :: MIT License
Classifier: Operating System :: OS Independent
Classifier: Development Status :: 3 - Alpha
Classifier: Intended Audience :: Developers
Classifier: Intended Audience :: Science/Research
Requires-Python: >=3.6
License-File: LICENSE
Provides-Extra: testing
Requires-Dist: pytest (>=6.0) ; extra == 'testing'
Requires-Dist: pytest-cov (>=2.10) ; extra == 'testing'
Requires-Dist: flake8 (>=3.9) ; extra == 'testing'
